datalabutils/DataMaker.py
datalabutils/__init__.py
datalabutils/datalabutils.py
datalabutils/photoz_utils.py
ucla_datalabutils-0.1.1.dist-info/AUTHORS.rst
ucla_datalabutils-0.1.1.dist-info/METADATA
ucla_datalabutils-0.1.1.dist-info/WHEEL
ucla_datalabutils-0.1.1.dist-info/top_level.txt
ucla_datalabutils-0.1.1.dist-info/RECORD
