Metadata-Version: 2.1
Name: ucla-datalabutils
Version: 0.1.1
Summary: Utility functions from UCLA Astrophysics Data Lab
Author-email: Tuan Do <tdo@astro.ucla.edu>
Maintainer-email: Tuan Do <tdo@astro.ucla.edu>
License: Not open source
Requires-Python: >=3.10
License-File: AUTHORS.rst
Requires-Dist: matplotlib
Requires-Dist: numpy
Requires-Dist: pandas
Requires-Dist: seaborn
Requires-Dist: tabulate
Requires-Dist: scikit-learn
Requires-Dist: astropy
Requires-Dist: scipy
Requires-Dist: tensorflow[tensorflow] >=2.11.0
